{"cameraMode":{"drawMode":0,"name":"Shaded","section":"Shading Mode"},"sceneLighting":true,"audioPlay":false,"sceneViewState":{"showFog":true,"showMaterialUpdate":false,"showSkybox":true,"showFlares":true,"showImageEffects":true,"showParticleSystems":true},"in2DMode":false,"pivot":{"x":10.648277282714844,"y":4.439168453216553,"z":-3.341527223587036},"rotation":{"x":0.07541171461343765,"y":-0.7123832106590271,"z":0.07745006680488587,"w":0.6934322118759155},"size":19.18691635131836,"orthographic":false}